[
  {
    "Template": "FestivalBuff",
    "Values": {
      "Standard": {
        "GUID": 141896,
        "Name": "BeerFestivalResidencesBuff",
        "IconFilename": "data/ui/2kimages/main/3dicons/icon_beer_2.png",
        "InfoDescription": 20111
      },
      "Text": {
        "LocaText": {
          "English": {
            "Text": "Beer Festival",
            "Status": "Exported",
            "ExportCount": 2
          }
        },
        "LineID": 25925
      },
      "PopulationUpgrade": "",
      "ResidenceUpgrade": {
        "AdditionalHappiness": 25,
        "GoodConsumptionUpgrade": {
          "Item": [
            {
              "ProvidedNeed": 1010216,
              "AmountInPercent": -100
            },
            {
              "ProvidedNeed": 1010214,
              "AmountInPercent": -100
            },
            {
              "ProvidedNeed": 1010257,
              "AmountInPercent": -100
            },
            {
              "ProvidedNeed": 120016,
              "AmountInPercent": -100
            }
          ]
        }
      },
      "ItemEffect": {
        "EffectTargets": {
          "Item": {
            "GUID": 190762
          }
        }
      },
      "Buff": "",
      "CultureUpgrade": "",
      "KontorUpgrade": "",
      "AttackableUpgrade": "",
      "AttackerUpgrade": "",
      "BuildingUpgrade": "",
      "FactoryUpgrade": "",
      "PassiveTradeGoodGenUpgrade": "",
      "ShipyardUpgrade": "",
      "VisitorHarborUpgrade": "",
      "VisitorUpgrade": ""
    }
  },
  {
    "Template": "FestivalBuff",
    "Values": {
      "Standard": {
        "GUID": 142449,
        "Name": "BeerFestivalProductionBuff",
        "IconFilename": "data/ui/2kimages/main/3dicons/icon_beer_2.png",
        "InfoDescription": 20111
      },
      "Text": {
        "LocaText": {
          "English": {
            "Text": "Beer Festival",
            "Status": "Exported",
            "ExportCount": 2
          }
        },
        "LineID": 28706
      },
      "PopulationUpgrade": "",
      "ResidenceUpgrade": "",
      "ItemEffect": {
        "EffectTargets": {
          "Item": {
            "GUID": 192566
          }
        }
      },
      "Buff": "",
      "CultureUpgrade": "",
      "KontorUpgrade": "",
      "AttackableUpgrade": "",
      "AttackerUpgrade": "",
      "BuildingUpgrade": {
        "WorkforceAmountUpgrade": {
          "Value": -25,
          "Percental": 1
        }
      },
      "FactoryUpgrade": {
        "ProductivityUpgrade": {
          "Value": 50,
          "Percental": 1
        }
      },
      "PassiveTradeGoodGenUpgrade": "",
      "ShipyardUpgrade": "",
      "VisitorHarborUpgrade": "",
      "VisitorUpgrade": ""
    }
  },
  {
    "Template": "FestivalBuff",
    "Values": {
      "Standard": {
        "GUID": 142451,
        "Name": "HarvestFestivalResidencesBuff",
        "IconFilename": "data/ui/2kimages/main/3dicons/icon_cereals_2.png",
        "InfoDescription": 20112
      },
      "Text": {
        "LocaText": {
          "English": {
            "Text": "Harvest Festival",
            "Status": "Exported",
            "ExportCount": 2
          }
        },
        "LineID": 28480
      },
      "PopulationUpgrade": "",
      "ResidenceUpgrade": {
        "AdditionalHappiness": 10,
        "TaxModifierInPercent": 10
      },
      "ItemEffect": {
        "EffectTargets": {
          "Item": {
            "GUID": 190762
          }
        }
      },
      "Buff": "",
      "CultureUpgrade": "",
      "KontorUpgrade": "",
      "AttackableUpgrade": "",
      "AttackerUpgrade": "",
      "BuildingUpgrade": "",
      "FactoryUpgrade": "",
      "PassiveTradeGoodGenUpgrade": "",
      "ShipyardUpgrade": "",
      "VisitorHarborUpgrade": "",
      "VisitorUpgrade": ""
    }
  },
  {
    "Template": "FestivalBuff",
    "Values": {
      "Standard": {
        "GUID": 142430,
        "Name": "HarvestFestivalProductionBuff",
        "IconFilename": "data/ui/2kimages/main/3dicons/icon_cereals_2.png",
        "InfoDescription": 20112
      },
      "Text": {
        "LocaText": {
          "English": {
            "Text": "Harvest Festival",
            "Status": "Exported",
            "ExportCount": 2
          }
        },
        "LineID": 28708
      },
      "PopulationUpgrade": "",
      "ResidenceUpgrade": "",
      "ItemEffect": {
        "EffectTargets": {
          "Item": {
            "GUID": 190865
          }
        }
      },
      "Buff": "",
      "CultureUpgrade": "",
      "KontorUpgrade": "",
      "AttackableUpgrade": "",
      "AttackerUpgrade": "",
      "BuildingUpgrade": {
        "MaintenanceUpgrade": {
          "Value": -100,
          "Percental": 1
        }
      },
      "FactoryUpgrade": {
        "ProductivityUpgrade": {
          "Value": 50,
          "Percental": 1
        },
        "AdditionalOutput": {
          "Item": [
            {
              "Product": 1010257,
              "AdditionalOutputCycle": 8,
              "Amount": 1
            },
            {
              "Product": 120016,
              "AdditionalOutputCycle": 9,
              "Amount": 1
            },
            {
              "Product": 1010259,
              "AdditionalOutputCycle": 10,
              "Amount": 1
            },
            {
              "Product": 1010258,
              "AdditionalOutputCycle": 11,
              "Amount": 1
            }
          ]
        }
      },
      "PassiveTradeGoodGenUpgrade": "",
      "ShipyardUpgrade": "",
      "VisitorHarborUpgrade": "",
      "VisitorUpgrade": ""
    }
  },
  {
    "Template": "FestivalBuff",
    "Values": {
      "Standard": {
        "GUID": 142453,
        "Name": "ArtsFestivalPublicBuff",
        "IconFilename": "data/ui/2kimages/main/3dicons/museum/icon_scroll_anthology_myths.png",
        "InfoDescription": 20113
      },
      "Text": {
        "LocaText": {
          "English": {
            "Text": "Arts Festival",
            "Status": "Exported",
            "ExportCount": 2
          }
        },
        "LineID": 28710
      },
      "PopulationUpgrade": "",
      "ResidenceUpgrade": "",
      "ItemEffect": {
        "EffectTargets": {
          "Item": {
            "GUID": 191501
          }
        }
      },
      "Buff": "",
      "CultureUpgrade": {
        "AttractivenessUpgrade": {
          "Value": 5
        }
      },
      "KontorUpgrade": "",
      "AttackableUpgrade": "",
      "AttackerUpgrade": "",
      "BuildingUpgrade": {
        "MaintenanceUpgrade": {
          "Value": -50,
          "Percental": 1
        }
      },
      "FactoryUpgrade": "",
      "PassiveTradeGoodGenUpgrade": "",
      "ShipyardUpgrade": "",
      "VisitorHarborUpgrade": "",
      "VisitorUpgrade": ""
    }
  },
  {
    "Template": "FestivalBuff",
    "Values": {
      "Standard": {
        "GUID": 142454,
        "Name": "ArtsFestivalCultureBuff",
        "IconFilename": "data/ui/2kimages/main/3dicons/museum/icon_scroll_anthology_myths.png",
        "InfoDescription": 20113
      },
      "Text": {
        "LocaText": {
          "English": {
            "Text": "Arts Festival",
            "Status": "Exported",
            "ExportCount": 2
          }
        },
        "LineID": 28711
      },
      "PopulationUpgrade": "",
      "ResidenceUpgrade": "",
      "ItemEffect": {
        "EffectTargets": {
          "Item": {
            "GUID": 193666
          }
        }
      },
      "Buff": "",
      "CultureUpgrade": {
        "AttractivenessUpgrade": {
          "Value": 5,
          "Percental": 1
        }
      },
      "KontorUpgrade": "",
      "AttackableUpgrade": "",
      "AttackerUpgrade": "",
      "BuildingUpgrade": {
        "MaintenanceUpgrade": {
          "Value": -100,
          "Percental": 1
        }
      },
      "FactoryUpgrade": "",
      "PassiveTradeGoodGenUpgrade": "",
      "ShipyardUpgrade": "",
      "VisitorHarborUpgrade": "",
      "VisitorUpgrade": ""
    }
  },
  {
    "Template": "FestivalBuff",
    "Values": {
      "Standard": {
        "GUID": 142432,
        "Name": "CommemorationFestivalResidencesBuff",
        "IconFilename": "data/ui/2kimages/main/3dicons/museum/icon_museum_sword_rare.png",
        "InfoDescription": 20114
      },
      "Text": {
        "LocaText": {
          "English": {
            "Text": "Commemoration Day",
            "Status": "Exported",
            "ExportCount": 2
          }
        },
        "LineID": 28482
      },
      "PopulationUpgrade": "",
      "ResidenceUpgrade": {
        "AdditionalHappiness": 10,
        "WorkforceModifierInPercent": 15
      },
      "ItemEffect": {
        "EffectTargets": {
          "Item": {
            "GUID": 190762
          }
        }
      },
      "Buff": "",
      "CultureUpgrade": "",
      "KontorUpgrade": "",
      "AttackableUpgrade": "",
      "AttackerUpgrade": "",
      "BuildingUpgrade": "",
      "FactoryUpgrade": "",
      "PassiveTradeGoodGenUpgrade": "",
      "ShipyardUpgrade": "",
      "VisitorHarborUpgrade": "",
      "VisitorUpgrade": ""
    }
  },
  {
    "Template": "FestivalBuff",
    "Values": {
      "Standard": {
        "GUID": 142456,
        "Name": "CommemorationFestivalProductionBuff",
        "IconFilename": "data/ui/2kimages/main/3dicons/museum/icon_museum_sword_rare.png",
        "InfoDescription": 20114
      },
      "Text": {
        "LocaText": {
          "English": {
            "Text": "Commemoration Day",
            "Status": "Exported",
            "ExportCount": 2
          }
        },
        "LineID": 28713
      },
      "PopulationUpgrade": "",
      "ResidenceUpgrade": "",
      "ItemEffect": {
        "EffectTargets": {
          "Item": {
            "GUID": 192436
          }
        }
      },
      "Buff": "",
      "CultureUpgrade": "",
      "KontorUpgrade": "",
      "AttackableUpgrade": "",
      "AttackerUpgrade": "",
      "BuildingUpgrade": "",
      "FactoryUpgrade": {
        "ProductivityUpgrade": {
          "Value": 300,
          "Percental": 1
        }
      },
      "PassiveTradeGoodGenUpgrade": "",
      "ShipyardUpgrade": "",
      "VisitorHarborUpgrade": "",
      "VisitorUpgrade": ""
    }
  },
  {
    "Template": "FestivalBuff",
    "Values": {
      "Standard": {
        "GUID": 142519,
        "Name": "CommemorationFestivalShipyardBuff",
        "IconFilename": "data/ui/2kimages/main/3dicons/museum/icon_museum_sword_rare.png",
        "InfoDescription": 20114
      },
      "Text": {
        "LocaText": {
          "English": {
            "Text": "Commemoration Day",
            "Status": "Exported",
            "ExportCount": 3
          }
        },
        "LineID": 29301
      },
      "PopulationUpgrade": "",
      "ResidenceUpgrade": "",
      "ItemEffect": {
        "EffectTargets": {
          "Item": {
            "GUID": 190783
          }
        }
      },
      "Buff": "",
      "CultureUpgrade": "",
      "KontorUpgrade": "",
      "AttackableUpgrade": "",
      "AttackerUpgrade": "",
      "BuildingUpgrade": "",
      "FactoryUpgrade": "",
      "PassiveTradeGoodGenUpgrade": "",
      "ShipyardUpgrade": {
        "ConstructionCostInPercent": -30,
        "ConstructionTimeInPercent": -30
      },
      "VisitorHarborUpgrade": "",
      "VisitorUpgrade": ""
    }
  },
  {
    "Template": "FestivalBuff",
    "Values": {
      "Standard": {
        "GUID": 142433,
        "Name": "CarnivalFestivalResidencesBuff",
        "IconFilename": "data/ui/2kimages/main/3dicons/narative_item/icon_fireworks.png",
        "InfoDescription": 20115
      },
      "Text": {
        "LocaText": {
          "English": {
            "Text": "Town Carnival",
            "Status": "Exported",
            "ExportCount": 2
          }
        },
        "LineID": 28483
      },
      "PopulationUpgrade": {
        "InputBenefitModifier": {
          "Item": [
            {
              "Product": 1010214,
              "AdditionalMoney": 5
            },
            {
              "Product": 1010216,
              "AdditionalMoney": 5
            },
            {
              "Product": 1010257,
              "AdditionalMoney": 5
            },
            {
              "Product": 120016,
              "AdditionalMoney": 5
            }
          ]
        }
      },
      "ResidenceUpgrade": {
        "AdditionalHappiness": 40
      },
      "ItemEffect": {
        "EffectTargets": {
          "Item": {
            "GUID": 190762
          }
        }
      },
      "Buff": "",
      "CultureUpgrade": "",
      "KontorUpgrade": "",
      "AttackableUpgrade": "",
      "AttackerUpgrade": "",
      "BuildingUpgrade": "",
      "FactoryUpgrade": "",
      "PassiveTradeGoodGenUpgrade": "",
      "ShipyardUpgrade": "",
      "VisitorHarborUpgrade": "",
      "VisitorUpgrade": ""
    }
  },
  {
    "Template": "FestivalBuff",
    "Values": {
      "Standard": {
        "GUID": 142462,
        "Name": "CarnivalFestivalVisitorsBuff",
        "IconFilename": "data/ui/2kimages/main/3dicons/narative_item/icon_fireworks.png",
        "InfoDescription": 20115
      },
      "Text": {
        "LocaText": {
          "English": {
            "Text": "Town Carnival",
            "Status": "Exported",
            "ExportCount": 2
          }
        },
        "LineID": 28715
      },
      "PopulationUpgrade": "",
      "ResidenceUpgrade": "",
      "ItemEffect": {
        "EffectTargets": {
          "Item": {
            "GUID": 191563
          }
        }
      },
      "Buff": "",
      "CultureUpgrade": "",
      "KontorUpgrade": "",
      "AttackableUpgrade": "",
      "AttackerUpgrade": "",
      "BuildingUpgrade": "",
      "FactoryUpgrade": "",
      "PassiveTradeGoodGenUpgrade": "",
      "ShipyardUpgrade": "",
      "VisitorHarborUpgrade": {
        "SpawnProbabilityFactor": {
          "Value": 100,
          "Percental": 1
        }
      },
      "VisitorUpgrade": ""
    }
  },
  {
    "Template": "FestivalBuff",
    "Values": {
      "Standard": {
        "GUID": 142919,
        "Name": "SpiritualFestivalAfricaResBuff",
        "IconFilename": "data/ui/2kimages/main/3dicons/goods_africa/icon_scriptures.png",
        "InfoDescription": 129653
      },
      "Text": {
        "LocaText": {
          "English": {
            "Text": "Holy Festival",
            "Status": "Exported",
            "ExportCount": 3
          }
        },
        "LineID": 44651
      },
      "PopulationUpgrade": "",
      "ResidenceUpgrade": {
        "AdditionalHappiness": 30,
        "GoodConsumptionUpgrade": {
          "Item": [
            {
              "ProvidedNeed": 114404,
              "AmountInPercent": -100
            },
            {
              "ProvidedNeed": 117698,
              "AmountInPercent": -100
            },
            {
              "ProvidedNeed": 117699,
              "AmountInPercent": -100
            }
          ]
        }
      },
      "ItemEffect": {
        "EffectTargets": {
          "Item": {
            "GUID": 190762
          }
        }
      },
      "Buff": "",
      "CultureUpgrade": "",
      "KontorUpgrade": "",
      "AttackableUpgrade": "",
      "AttackerUpgrade": "",
      "BuildingUpgrade": "",
      "FactoryUpgrade": "",
      "PassiveTradeGoodGenUpgrade": "",
      "ShipyardUpgrade": "",
      "VisitorHarborUpgrade": "",
      "VisitorUpgrade": ""
    }
  },
  {
    "Template": "FestivalBuff",
    "Values": {
      "Standard": {
        "GUID": 142923,
        "Name": "SpiritualFestivalAfricaProdBuff",
        "IconFilename": "data/ui/2kimages/main/3dicons/goods_africa/icon_scriptures.png",
        "InfoDescription": 129653
      },
      "Text": {
        "LocaText": {
          "English": {
            "Text": "Holy Festival",
            "Status": "Exported",
            "ExportCount": 3
          }
        },
        "LineID": 44652
      },
      "PopulationUpgrade": "",
      "ResidenceUpgrade": "",
      "ItemEffect": {
        "EffectTargets": {
          "Item": {
            "GUID": 114470
          }
        }
      },
      "Buff": "",
      "CultureUpgrade": "",
      "KontorUpgrade": "",
      "AttackableUpgrade": "",
      "AttackerUpgrade": "",
      "BuildingUpgrade": "",
      "FactoryUpgrade": {
        "AdditionalOutput": {
          "Item": [
            {
              "Product": 117702,
              "AdditionalOutputCycle": 2,
              "Amount": 1
            },
            {
              "Product": 114390,
              "AdditionalOutputCycle": 3,
              "Amount": 1
            },
            {
              "Product": 114414,
              "AdditionalOutputCycle": 4,
              "Amount": 1
            }
          ]
        }
      },
      "PassiveTradeGoodGenUpgrade": "",
      "ShipyardUpgrade": "",
      "VisitorHarborUpgrade": "",
      "VisitorUpgrade": ""
    }
  },
  {
    "Template": "FestivalBuff",
    "Values": {
      "Standard": {
        "GUID": 142924,
        "Name": "HarvestFestivalAfricaResBuff",
        "IconFilename": "data/ui/2kimages/main/3dicons/goods_africa/icon_teff_grass.png",
        "InfoDescription": 129654
      },
      "Text": {
        "LocaText": {
          "English": {
            "Text": "Festival of Life",
            "Status": "Exported",
            "ExportCount": 3
          }
        },
        "LineID": 44653
      },
      "PopulationUpgrade": "",
      "ResidenceUpgrade": {
        "AdditionalHappiness": 20,
        "TaxModifierInPercent": 25
      },
      "ItemEffect": {
        "EffectTargets": {
          "Item": {
            "GUID": 190762
          }
        }
      },
      "Buff": "",
      "CultureUpgrade": "",
      "KontorUpgrade": "",
      "AttackableUpgrade": "",
      "AttackerUpgrade": "",
      "BuildingUpgrade": "",
      "FactoryUpgrade": "",
      "PassiveTradeGoodGenUpgrade": "",
      "ShipyardUpgrade": "",
      "VisitorHarborUpgrade": "",
      "VisitorUpgrade": ""
    }
  },
  {
    "Template": "FestivalBuff",
    "Values": {
      "Standard": {
        "GUID": 142925,
        "Name": "HarvestFestivalAfricaProdBuff",
        "IconFilename": "data/ui/2kimages/main/3dicons/goods_africa/icon_teff_grass.png",
        "InfoDescription": 129654
      },
      "Text": {
        "LocaText": {
          "English": {
            "Text": "Festival of Life",
            "Status": "Exported",
            "ExportCount": 3
          }
        },
        "LineID": 44654
      },
      "PopulationUpgrade": "",
      "ResidenceUpgrade": "",
      "ItemEffect": {
        "EffectTargets": {
          "Item": {
            "GUID": 193959
          }
        }
      },
      "Buff": "",
      "CultureUpgrade": "",
      "KontorUpgrade": "",
      "AttackableUpgrade": "",
      "AttackerUpgrade": "",
      "BuildingUpgrade": {
        "MaintenanceUpgrade": {
          "Value": -100,
          "Percental": 1
        }
      },
      "FactoryUpgrade": {
        "ProductivityUpgrade": {
          "Value": 100,
          "Percental": 1
        }
      },
      "PassiveTradeGoodGenUpgrade": "",
      "ShipyardUpgrade": "",
      "VisitorHarborUpgrade": "",
      "VisitorUpgrade": ""
    }
  },
  {
    "Template": "FestivalBuff",
    "Values": {
      "Standard": {
        "GUID": 142926,
        "Name": "TradeFestivalAfricaResBuff",
        "IconFilename": "data/ui/2kimages/main/3dicons/goods_africa/icon_lanterns.png",
        "InfoDescription": 129655
      },
      "Text": {
        "LocaText": {
          "English": {
            "Text": "Festival of Hytia",
            "Status": "Exported",
            "ExportCount": 3
          }
        },
        "LineID": 44655
      },
      "PopulationUpgrade": "",
      "ResidenceUpgrade": {
        "AdditionalHappiness": 10,
        "GoodConsumptionUpgrade": {
          "Item": [
            {
              "ProvidedNeed": 114401,
              "AmountInPercent": -100
            },
            {
              "ProvidedNeed": 118724,
              "AmountInPercent": -100
            },
            {
              "ProvidedNeed": 114414,
              "AmountInPercent": -100
            },
            {
              "ProvidedNeed": 117699,
              "AmountInPercent": -100
            }
          ]
        }
      },
      "ItemEffect": {
        "EffectTargets": {
          "Item": {
            "GUID": 190762
          }
        }
      },
      "Buff": "",
      "CultureUpgrade": "",
      "KontorUpgrade": "",
      "AttackableUpgrade": "",
      "AttackerUpgrade": "",
      "BuildingUpgrade": "",
      "FactoryUpgrade": "",
      "PassiveTradeGoodGenUpgrade": "",
      "ShipyardUpgrade": "",
      "VisitorHarborUpgrade": "",
      "VisitorUpgrade": ""
    }
  },
  {
    "Template": "FestivalBuff",
    "Values": {
      "Standard": {
        "GUID": 142927,
        "Name": "TradeFestivalAfricaProdBuff",
        "IconFilename": "data/ui/2kimages/main/3dicons/goods_africa/icon_lanterns.png",
        "InfoDescription": 129655
      },
      "Text": {
        "LocaText": {
          "English": {
            "Text": "Festival of Hytia",
            "Status": "Exported",
            "ExportCount": 3
          }
        },
        "LineID": 44656
      },
      "PopulationUpgrade": "",
      "ResidenceUpgrade": "",
      "ItemEffect": {
        "EffectTargets": {
          "Item": {
            "GUID": 193960
          }
        }
      },
      "Buff": "",
      "CultureUpgrade": "",
      "KontorUpgrade": "",
      "AttackableUpgrade": "",
      "AttackerUpgrade": "",
      "BuildingUpgrade": "",
      "FactoryUpgrade": {
        "ProductivityUpgrade": {
          "Value": 50,
          "Percental": 1
        },
        "AdditionalOutput": {
          "Item": [
            {
              "Product": 1010201,
              "AdditionalOutputCycle": 7,
              "Amount": 1
            },
            {
              "Product": 1010252,
              "AdditionalOutputCycle": 8,
              "Amount": 1
            },
            {
              "Product": 120008,
              "AdditionalOutputCycle": 9,
              "Amount": 1
            },
            {
              "Product": 120030,
              "AdditionalOutputCycle": 10,
              "Amount": 1
            },
            {
              "Product": 1010253,
              "AdditionalOutputCycle": 11,
              "Amount": 1
            },
            {
              "Product": 1010241,
              "AdditionalOutputCycle": 12,
              "Amount": 1
            }
          ]
        }
      },
      "PassiveTradeGoodGenUpgrade": "",
      "ShipyardUpgrade": "",
      "VisitorHarborUpgrade": "",
      "VisitorUpgrade": ""
    }
  },
  {
    "Template": "FestivalBuff",
    "Values": {
      "Standard": {
        "GUID": 111831,
        "Name": "AnarchyFestivalResidencesBuff",
        "IconFilename": "data/ui/2kimages/main/3dicons/icon_anarchist.png",
        "InfoDescription": 111837
      },
      "Text": {
        "LocaText": {
          "English": {
            "Text": "Festival of Reason",
            "Status": "Exported",
            "ExportCount": 3
          }
        },
        "LineID": 31423
      },
      "PopulationUpgrade": "",
      "ResidenceUpgrade": {
        "AdditionalHappiness": 25,
        "GoodConsumptionUpgrade": {
          "Item": [
            {
              "ProvidedNeed": 1010216,
              "AmountInPercent": -100
            },
            {
              "ProvidedNeed": 1010214,
              "AmountInPercent": -100
            },
            {
              "ProvidedNeed": 1010257,
              "AmountInPercent": -100
            },
            {
              "ProvidedNeed": 120016,
              "AmountInPercent": -100
            }
          ]
        }
      },
      "ItemEffect": {
        "EffectTargets": {
          "Item": {
            "GUID": 190762
          }
        }
      },
      "Buff": "",
      "CultureUpgrade": "",
      "KontorUpgrade": "",
      "AttackableUpgrade": "",
      "AttackerUpgrade": "",
      "BuildingUpgrade": "",
      "FactoryUpgrade": "",
      "PassiveTradeGoodGenUpgrade": "",
      "ShipyardUpgrade": "",
      "VisitorHarborUpgrade": "",
      "VisitorUpgrade": ""
    }
  },
  {
    "Template": "FestivalBuff",
    "Values": {
      "Standard": {
        "GUID": 111832,
        "Name": "AnarchyFestivalProductionBuff",
        "IconFilename": "data/ui/2kimages/main/3dicons/icon_anarchist.png",
        "InfoDescription": 111837
      },
      "Text": {
        "LocaText": {
          "English": {
            "Text": "Festival of Reason",
            "Status": "Exported",
            "ExportCount": 3
          }
        },
        "LineID": 31424
      },
      "PopulationUpgrade": "",
      "ResidenceUpgrade": "",
      "ItemEffect": {
        "EffectTargets": {
          "Item": {
            "GUID": 193856
          }
        }
      },
      "Buff": "",
      "CultureUpgrade": "",
      "KontorUpgrade": "",
      "AttackableUpgrade": "",
      "AttackerUpgrade": "",
      "BuildingUpgrade": {
        "MaintenanceUpgrade": {
          "Value": -10,
          "Percental": 1
        }
      },
      "FactoryUpgrade": {
        "ProductivityUpgrade": {
          "Value": 20,
          "Percental": 1
        }
      },
      "PassiveTradeGoodGenUpgrade": "",
      "ShipyardUpgrade": "",
      "VisitorHarborUpgrade": "",
      "VisitorUpgrade": ""
    }
  }
]